{
  "CreateStar": {
    "TextureName": "BlockSprites/Blocks&Pipes",
    "SourceFrames": [
      {
        "X": 224,
        "Y": 106,
        "Width": 15,
        "Height": 16
      }
    ],
    "FrameDelay": 0.08,
    "Scale": 1.5
  },

  "CreateYoshiEgg": {
    "TextureName": "BlockSprites/Blocks&Pipes",
    "SourceFrames": [
      {
        "X": 286,
        "Y": 105,
        "Width": 14,
        "Height": 16
      }
    ],
    "FrameDelay": 0.08,
    "Scale": 1.5
  },

  "CreateYoshiCoinAnimated": {
    "TextureName": "BlockSprites/Blocks&Pipes2",
    "SourceFrames": [
      {
        "X": 0,
        "Y": 32,
        "Width": 16,
        "Height": 32
      },
      {
        "X": 16,
        "Y": 32,
        "Width": 16,
        "Height": 32
      },
      {
        "X": 32,
        "Y": 32,
        "Width": 16,
        "Height": 32
      },
      {
        "X": 48,
        "Y": 32,
        "Width": 16,
        "Height": 32
      },
      {
        "X": 64,
        "Y": 32,
        "Width": 16,
        "Height": 32
      },
      {
        "X": 80,
        "Y": 32,
        "Width": 16,
        "Height": 32
      }
    ],
    "FrameDelay": 0.08,
    "Scale": 1.5
  },

  "CreateFireFlower": {
    "TextureName": "BlockSprites/Blocks&Pipes",
    "SourceFrames": [
      {
        "X": 202,
        "Y": 107,
        "Width": 16,
        "Height": 16
      }
    ],
    "FrameDelay": 0.08,
    "Scale": 1.5
  },

  "CreateRedMushroom": {
    "TextureName": "BlockSprites/Blocks&Pipes",
    "SourceFrames": [
      {
        "X": 182,
        "Y": 107,
        "Width": 16,
        "Height": 16
      }
    ],
    "FrameDelay": 0.08,
    "Scale": 1.5
  },

  "CreateQuestionMarkBlockAnimated": {
    "TextureName": "BlockSprites/Blocks&Pipes2",
    "SourceFrames": [
      {
        "X": 0,
        "Y": 64,
        "Width": 16,
        "Height": 16
      },
      {
        "X": 16,
        "Y": 64,
        "Width": 16,
        "Height": 16
      },
      {
        "X": 32,
        "Y": 64,
        "Width": 16,
        "Height": 16
      },
      {
        "X": 48,
        "Y": 64,
        "Width": 16,
        "Height": 16
      }
    ],
    "FrameDelay": 0.08,
    "Scale": 1.5
  },

  "CreateActivatedBlock": {
    "TextureName": "BlockSprites/Blocks&Pipes",
    "SourceFrames": [
      {
        "X": 49,
        "Y": 107,
        "Width": 16,
        "Height": 16
      }
    ],
    "FrameDelay": 0.08,
    "Scale": 1.5
  },

  "CreateEmptyBlock": {
    "TextureName": "BlockSprites/Blocks&Pipes",
    "SourceFrames": [
      {
        "X": 0,
        "Y": 0,
        "Width": 16,
        "Height": 16
      }
    ],
    "FrameDelay": 0.08,
    "Scale": 1.5
  },

  "CreateBrickBlock": {
    "TextureName": "BlockSprites/BrickBlock",
    "SourceFrames": [
      {
        "X": 272,
        "Y": 112,
        "Width": 16,
        "Height": 16
      }
    ],
    "FrameDelay": 0.08,
    "Scale": 1.5
  },

  "CreateSkullBlock": {
    "TextureName": "BlockSprites/Blocks&Pipes",
    "SourceFrames": [
      {
        "X": 71,
        "Y": 107,
        "Width": 16,
        "Height": 16
      }
    ],
    "FrameDelay": 0.08,
    "Scale": 1.5
  },

  "CreateSpinBlockStatic": {
    "TextureName": "BlockSprites/Blocks&Pipes",
    "SourceFrames": [
      {
        "X": 0,
        "Y": 80,
        "Width": 16,
        "Height": 16
      }
    ],
    "FrameDelay": 0.08,
    "Scale": 1.5
  },

  "CreateSpinBlockAnimated": {
    "TextureName": "BlockSprites/Blocks&Pipes",
    "SourceFrames": [
      {
        "X": 0,
        "Y": 80,
        "Width": 16,
        "Height": 16
      },
      {
        "X": 16,
        "Y": 80,
        "Width": 16,
        "Height": 16
      },
      {
        "X": 32,
        "Y": 80,
        "Width": 16,
        "Height": 16
      },
      {
        "X": 48,
        "Y": 80,
        "Width": 16,
        "Height": 16
      }
    ],
    "FrameDelay": 0.08,
    "Scale": 1.5
  },

  "CreateGreenPipe": {
    "TextureName": "BlockSprites/Blocks&Pipes2",
    "SourceFrames": [
      {
        "X": 96,
        "Y": 0,
        "Width": 32,
        "Height": 32
      }
    ],
    "FrameDelay": 0.08,
    "Scale": 1.5
  },

  "CreateYellowPipe": {
    "TextureName": "BlockSprites/Blocks&Pipes2",
    "SourceFrames": [
      {
        "X": 128,
        "Y": 0,
        "Width": 32,
        "Height": 32
      }
    ],
    "FrameDelay": 0.08,
    "Scale": 1.5
  },

  "CreateBluePipe": {
    "TextureName": "BlockSprites/Blocks&Pipes2",
    "SourceFrames": [
      {
        "X": 160,
        "Y": 0,
        "Width": 32,
        "Height": 32
      }
    ],
    "FrameDelay": 0.08,
    "Scale": 1.5
  },

  "CreateLeftGreenFloor": {
    "TextureName": "BlockSprites/Blocks&Pipes2",
    "SourceFrames": [
      {
        "X": 0,
        "Y": 256,
        "Width": 16,
        "Height": 15
      }
    ],
    "FrameDelay": 0.08,
    "Scale": 1.5
  },

  "CreateMiddleGreenFloor": {
    "TextureName": "BlockSprites/Blocks&Pipes2",
    "SourceFrames": [
      {
        "X": 16,
        "Y": 256,
        "Width": 16,
        "Height": 15
      }
    ],
    "FrameDelay": 0.08,
    "Scale": 1.5
  },

  "CreateRightGreenFloor": {
    "TextureName": "BlockSprites/Blocks&Pipes2",
    "SourceFrames": [
      {
        "X": 32,
        "Y": 256,
        "Width": 16,
        "Height": 15
      }
    ],
    "FrameDelay": 0.08,
    "Scale": 1.5
  }
}